{"embedTypes":["iframe"],"language":"en","defaultLanguage":"es","license":"U","extraTitle":"Quiz sobre el ciclo for","title":"Quiz sobre el ciclo for","mainLibrary":"H5P.QuestionSet","preloadedDependencies":[{"machineName":"H5P.MultiChoice","majorVersion":1,"minorVersion":16},{"machineName":"FontAwesome","majorVersion":4,"minorVersion":5},{"machineName":"EmbeddedJS","majorVersion":1,"minorVersion":0},{"machineName":"H5P.JoubelUI","majorVersion":1,"minorVersion":3},{"machineName":"H5P.Transition","majorVersion":1,"minorVersion":0},{"machineName":"Drop","majorVersion":1,"minorVersion":0},{"machineName":"Tether","majorVersion":1,"minorVersion":0},{"machineName":"H5P.FontIcons","majorVersion":1,"minorVersion":0},{"machineName":"H5P.Question","majorVersion":1,"minorVersion":5},{"machineName":"H5P.Blanks","majorVersion":1,"minorVersion":14},{"machineName":"H5P.TextUtilities","majorVersion":1,"minorVersion":3},{"machineName":"H5P.TrueFalse","majorVersion":1,"minorVersion":8},{"machineName":"H5P.MarkTheWords","majorVersion":1,"minorVersion":11},{"machineName":"H5P.Video","majorVersion":1,"minorVersion":6},{"machineName":"H5P.QuestionSet","majorVersion":1,"minorVersion":20}]}